google_news_feed/__init__.py
google_news_feed-1.1.0.dist-info/METADATA
google_news_feed-1.1.0.dist-info/WHEEL
google_news_feed-1.1.0.dist-info/licenses/LICENSE
google_news_feed-1.1.0.dist-info/RECORD
