Metadata-Version: 2.1
Name: google_news_feed
Version: 1.1.0
Summary: A simple python library to consume the google news rss feed
Project-URL: Homepage, https://github.com/LLukas22/Google-News-RSS
Project-URL: Bug Tracker, https://github.com/LLukas22/Google-News-RSS/issues
Author: Lukas Kreussel
License: MIT License
License-File: LICENSE
Classifier: License :: OSI Approved :: MIT License
Classifier: Operating System :: OS Independent
Classifier: Programming Language :: Python :: 3
Requires-Python: >=3.10
Requires-Dist: aiohttp>=3.8.4
Requires-Dist: beautifulsoup4>=4.12.2
Requires-Dist: dateparser>=1.1.1
Requires-Dist: lxml>=4.9.0
Requires-Dist: requests>=2.31.0
